MANIFEST.in
setup.py
CmakePy.egg-info/PKG-INFO
CmakePy.egg-info/SOURCES.txt
CmakePy.egg-info/dependency_links.txt
CmakePy.egg-info/entry_points.txt
CmakePy.egg-info/requires.txt
CmakePy.egg-info/top_level.txt
cmakepy/__init__.py
cmakepy/cmakepy.py
cmakepy/templates/CMakeLists.txt
cmakepy/templates/__init__.py
cmakepy/templates/main.cpp