Metadata-Version: 1.0
Name: CmakePy
Version: 0.1.1
Summary: Creates a new cmake project
Home-page: https://github.com/jlesquembre/cmakepy
Author: Jose Luis Lafuente
Author-email: joseluis@japeto.com
License: GPLv3
Keywords: cmake c++
Platform: UNKNOWN
